{"song":{"player1":"bf-christmas","sectionLengths":[],"notes":[{"lengthInSteps":16,"sectionNotes":[[0,2,0],[150,1,0],[300,2,0],[450,0,0],[600,2,0],[750,3,0],[900,2,0],[1050,0,0]],"typeOfSection":0,"mustHitSection":false,"changeBPM":false,"bpm":95},{"lengthInSteps":16,"sectionNotes":[[1800,2,225],[2100,1,225],[1350,3,75],[1500,0,75],[1650,3,75],[1200,1,75]],"typeOfSection":0,"mustHitSection":false,"changeBPM":false,"bpm":110},{"lengthInSteps":16,"sectionNotes":[[2400,3,0],[2550,1,0],[2700,3,0],[2850,0,0],[3000,2,0],[3150,1,0],[3300,0,0],[3450,3,0]],"typeOfSection":0,"mustHitSection":false,"changeBPM":false,"bpm":110},{"lengthInSteps":16,"sectionNotes":[[4200,2,225],[4500,1,225],[3600,1,75],[3750,2,75],[3900,3,75],[4050,0,75]],"typeOfSection":0,"mustHitSection":false,"changeBPM":false,"bpm":110},{"lengthInSteps":16,"sectionNotes":[[4800,1,0],[4950,2,0],[5100,1,0],[5250,3,0],[5400,1,0],[5550,0,0],[5700,1,0],[5850,3,0]],"typeOfSection":0,"mustHitSection":true,"changeBPM":false,"bpm":110},{"lengthInSteps":16,"sectionNotes":[[6000,2,75],[6150,0,75],[6300,3,75],[6450,0,75],[6600,1,225],[6900,2,225]],"typeOfSection":0,"mustHitSection":true,"changeBPM":false,"bpm":110},{"lengthInSteps":16,"sectionNotes":[[7200,0,0],[7350,2,0],[7500,0,0],[7650,3,0],[7800,1,0],[7950,2,0],[8100,3,0],[8250,0,0]],"typeOfSection":0,"mustHitSection":true,"changeBPM":false,"bpm":110},{"lengthInSteps":16,"sectionNotes":[[9000,3,225],[9300,2,225],[8400,2,225],[8700,1,75],[8850,0,75]],"typeOfSection":0,"mustHitSection":true,"changeBPM":false,"bpm":110},{"lengthInSteps":16,"sectionNotes":[[9600,7,150],[9600,2,0],[9750,1,0],[9900,2,0],[10050,0,0],[10200,3,225],[10500,1,225]],"typeOfSection":0,"mustHitSection":false,"changeBPM":false,"bpm":110},{"lengthInSteps":16,"sectionNotes":[[10800,1,0],[10950,2,0],[11100,0,0],[11250,1,0],[11400,3,225],[11700,2,225]],"typeOfSection":0,"mustHitSection":false,"changeBPM":false,"bpm":110},{"lengthInSteps":16,"sectionNotes":[[12000,6,225],[12000,0,225],[12300,4,225],[12300,1,225],[12600,3,225],[12900,2,225]],"typeOfSection":0,"mustHitSection":false,"changeBPM":false,"bpm":110},{"lengthInSteps":16,"sectionNotes":[[13650,6,225],[14100,5,150],[13200,4,75],[13800,0,0],[13950,2,0],[14100,3,0],[13200,1,225],[13500,3,225]],"typeOfSection":0,"mustHitSection":false,"changeBPM":false,"bpm":110},{"lengthInSteps":16,"sectionNotes":[[14400,1,0],[14550,0,0],[14700,2,0],[14850,1,0],[15000,3,225],[15300,2,225],[14400,6,225],[14700,4,225]],"typeOfSection":0,"mustHitSection":true,"changeBPM":false,"bpm":110},{"lengthInSteps":16,"sectionNotes":[[16200,2,225],[15600,2,0],[15750,1,0],[15900,3,0],[16050,0,0],[16500,3,225]],"typeOfSection":0,"mustHitSection":true,"changeBPM":false,"bpm":110},{"lengthInSteps":16,"sectionNotes":[[17100,1,0],[17250,2,0],[17700,2,0],[17850,3,0],[16800,3,225],[17400,0,225],[17100,4,225],[16800,6,225]],"typeOfSection":0,"mustHitSection":true,"changeBPM":false,"bpm":110},{"lengthInSteps":16,"sectionNotes":[[18600,3,0],[18750,2,0],[18900,3,225],[18000,1,225],[18300,0,225]],"typeOfSection":0,"mustHitSection":true,"changeBPM":false,"bpm":110},{"lengthInSteps":16,"sectionNotes":[[19200,3,375],[19650,1,375],[20100,2,375]],"typeOfSection":0,"mustHitSection":false,"changeBPM":false,"bpm":110},{"lengthInSteps":16,"sectionNotes":[[20550,0,0],[21000,3,225],[21300,2,225],[20700,1,225]],"typeOfSection":0,"mustHitSection":false,"changeBPM":false,"bpm":110},{"lengthInSteps":16,"sectionNotes":[[21600,0,450],[22125,1,300],[22500,3,225]],"typeOfSection":0,"mustHitSection":false,"changeBPM":false,"bpm":110},{"lengthInSteps":16,"sectionNotes":[[22800,2,0],[23100,1,0],[23250,3,0],[23400,1,225],[23700,2,225]],"typeOfSection":0,"mustHitSection":false,"changeBPM":false,"bpm":110},{"lengthInSteps":16,"sectionNotes":[[24900,1,0],[25050,3,0],[24000,0,225],[24600,2,225],[24450,3,0],[24300,1,0]],"typeOfSection":0,"mustHitSection":false,"changeBPM":false,"bpm":110},{"lengthInSteps":16,"sectionNotes":[[25200,0,225],[25500,3,225],[25800,1,225],[26100,3,225]],"typeOfSection":0,"mustHitSection":false,"changeBPM":false,"bpm":110},{"lengthInSteps":16,"sectionNotes":[[26700,3,0],[26850,1,0],[26400,0,225],[27000,2,225],[27300,0,225]],"typeOfSection":0,"mustHitSection":false,"changeBPM":false,"bpm":110},{"lengthInSteps":16,"sectionNotes":[[28200,0,150],[27900,1,225],[27600,2,225],[28500,3,225]],"typeOfSection":0,"mustHitSection":false,"changeBPM":false,"bpm":110},{"lengthInSteps":16,"sectionNotes":[[28800,6,225],[28800,0,375],[29250,2,375],[29700,1,375]],"typeOfSection":0,"mustHitSection":true,"changeBPM":false,"bpm":110},{"lengthInSteps":16,"sectionNotes":[[30150,3,0],[30900,1,225],[30600,0,225],[30300,2,225]],"typeOfSection":0,"mustHitSection":true,"changeBPM":false,"bpm":110},{"lengthInSteps":16,"sectionNotes":[[31200,3,375],[31650,2,375],[32100,0,225]],"typeOfSection":0,"mustHitSection":true,"changeBPM":false,"bpm":110},{"lengthInSteps":16,"sectionNotes":[[32700,2,0],[32850,0,0],[32400,1,225],[33000,2,225],[33300,1,225]],"typeOfSection":0,"mustHitSection":true,"changeBPM":false,"bpm":110},{"lengthInSteps":16,"sectionNotes":[[33600,3,225],[33900,2,0],[34050,0,0],[34500,2,0],[34650,0,0],[34200,1,225]],"typeOfSection":0,"mustHitSection":true,"changeBPM":false,"bpm":110},{"lengthInSteps":16,"sectionNotes":[[34800,3,225],[35100,0,225],[35400,2,225],[35700,0,225]],"typeOfSection":0,"mustHitSection":true,"changeBPM":false,"bpm":110},{"lengthInSteps":16,"sectionNotes":[[36000,3,225],[36300,0,225],[36600,2,225],[36900,3,225]],"typeOfSection":0,"mustHitSection":true,"changeBPM":false,"bpm":110},{"lengthInSteps":16,"sectionNotes":[[37800,1,0],[37950,0,0],[37200,1,225],[37500,2,225],[38100,3,225]],"typeOfSection":0,"mustHitSection":true,"changeBPM":false,"bpm":110},{"lengthInSteps":16,"sectionNotes":[[38400,6,225],[38400,3,225],[38700,0,0],[38850,2,0],[39300,1,225],[39000,0,225]],"typeOfSection":0,"mustHitSection":false,"changeBPM":false,"bpm":110},{"lengthInSteps":16,"sectionNotes":[[39600,1,0],[39750,2,0],[39900,1,0],[40050,2,0],[40200,0,0],[40350,3,0],[40500,0,225]],"typeOfSection":0,"mustHitSection":false,"changeBPM":false,"bpm":110},{"lengthInSteps":16,"sectionNotes":[[40800,1,225],[41100,1,0],[41250,2,0],[41400,0,225],[41700,3,225]],"typeOfSection":0,"mustHitSection":false,"changeBPM":false,"bpm":110},{"lengthInSteps":16,"sectionNotes":[[42000,0,0],[42150,3,0],[42300,1,0],[42450,2,0],[42900,3,225],[42600,0,225]],"typeOfSection":0,"mustHitSection":false,"changeBPM":false,"bpm":110},{"lengthInSteps":16,"sectionNotes":[[43200,0,225],[43500,3,0],[43800,3,225],[43650,1,0],[44100,2,225]],"typeOfSection":0,"mustHitSection":true,"changeBPM":false,"bpm":110},{"lengthInSteps":16,"sectionNotes":[[44700,1,0],[44850,0,0],[44400,2,225],[45000,2,225],[45300,1,225]],"typeOfSection":0,"mustHitSection":true,"changeBPM":false,"bpm":110},{"lengthInSteps":16,"sectionNotes":[[45600,1,0],[45750,2,0],[45900,0,0],[46050,3,0],[46200,2,0],[46350,3,0],[46500,0,0],[46650,3,0]],"typeOfSection":0,"mustHitSection":true,"changeBPM":false,"bpm":110},{"lengthInSteps":16,"sectionNotes":[[47700,3,225],[47400,0,225],[47100,2,225],[46800,1,225]],"typeOfSection":0,"mustHitSection":true,"changeBPM":false,"bpm":110},{"lengthInSteps":16,"sectionNotes":[[48000,1,0],[48150,2,0],[48300,0,0],[48450,1,0],[48600,2,225],[48900,3,225]],"typeOfSection":0,"mustHitSection":false,"changeBPM":false,"bpm":110},{"lengthInSteps":16,"sectionNotes":[[49200,2,0],[49350,1,0],[49500,2,0],[49650,0,0],[50100,1,225],[49800,3,225]],"typeOfSection":0,"mustHitSection":false,"changeBPM":false,"bpm":110},{"lengthInSteps":16,"sectionNotes":[[50400,1,0],[50550,2,0],[50700,0,0],[50850,1,0],[51000,2,225],[51300,1,225]],"typeOfSection":0,"mustHitSection":false,"changeBPM":false,"bpm":110},{"lengthInSteps":16,"sectionNotes":[[51600,3,225],[51900,0,225],[52200,2,225],[52500,1,225]],"typeOfSection":0,"mustHitSection":false,"changeBPM":false,"bpm":110},{"lengthInSteps":16,"sectionNotes":[[52800,4,525],[52800,2,0],[52950,1,0],[53100,3,0],[53250,2,0],[53400,1,225],[53700,0,225]],"typeOfSection":0,"mustHitSection":true,"changeBPM":false,"bpm":110},{"lengthInSteps":16,"sectionNotes":[[54000,1,0],[54150,2,0],[54300,1,0],[54450,3,0],[54600,0,225],[54900,2,225]],"typeOfSection":0,"mustHitSection":true,"changeBPM":false,"bpm":110},{"sectionNotes":[[55200,2,0],[55350,1,0],[55500,3,0],[55650,2,0],[55800,1,225],[56100,2,225]],"typeOfSection":0,"lengthInSteps":16,"altAnim":false,"mustHitSection":true,"changeBPM":false,"bpm":110},{"sectionNotes":[[56400,3,525],[57000,0,225],[57300,2,225]],"typeOfSection":0,"lengthInSteps":16,"altAnim":false,"mustHitSection":true,"changeBPM":false,"bpm":100},{"lengthInSteps":16,"typeOfSection":0,"sectionNotes":[[57600,4,525],[57600,3,375],[58050,1,375],[58500,2,375]],"altAnim":false,"bpm":100,"changeBPM":false,"mustHitSection":false},{"lengthInSteps":16,"typeOfSection":0,"sectionNotes":[[59400,3,225],[59700,2,225],[58950,0,0],[59100,1,225]],"altAnim":false,"bpm":200,"changeBPM":false,"mustHitSection":false},{"lengthInSteps":16,"typeOfSection":0,"sectionNotes":[[60900,3,225],[60450,1,375],[60000,0,375]],"altAnim":false,"bpm":200,"changeBPM":false,"mustHitSection":false},{"lengthInSteps":16,"typeOfSection":0,"sectionNotes":[[61500,1,0],[61650,3,0],[62100,2,225],[61800,1,225],[61200,2,225]],"altAnim":false,"bpm":200,"changeBPM":false,"mustHitSection":false},{"lengthInSteps":16,"typeOfSection":0,"sectionNotes":[[62850,3,0],[62700,1,0],[62400,0,225],[63000,2,225],[63300,1,0],[63450,3,0]],"altAnim":false,"bpm":200,"changeBPM":false,"mustHitSection":false},{"lengthInSteps":16,"typeOfSection":0,"sectionNotes":[[64500,3,225],[64200,1,225],[63900,3,225],[63600,0,225]],"altAnim":false,"bpm":200,"changeBPM":false,"mustHitSection":false},{"lengthInSteps":16,"typeOfSection":0,"sectionNotes":[[65100,3,0],[65250,1,0],[64800,0,225],[65400,2,225],[65700,0,225]],"altAnim":false,"bpm":200,"changeBPM":false,"mustHitSection":false},{"lengthInSteps":16,"typeOfSection":0,"sectionNotes":[[66000,2,225],[66300,1,225],[66900,3,225],[66600,0,150]],"altAnim":false,"bpm":200,"changeBPM":false,"mustHitSection":false},{"lengthInSteps":16,"typeOfSection":0,"sectionNotes":[[67200,6,225],[67200,0,375],[67650,2,375],[68100,1,375]],"altAnim":false,"bpm":200,"changeBPM":false,"mustHitSection":true},{"lengthInSteps":16,"typeOfSection":0,"sectionNotes":[[68550,3,0],[69000,0,225],[69300,1,225],[68700,2,225]],"altAnim":false,"bpm":200,"changeBPM":false,"mustHitSection":true},{"lengthInSteps":16,"typeOfSection":0,"sectionNotes":[[70500,0,225],[70050,2,375],[69600,3,375]],"altAnim":false,"bpm":200,"changeBPM":false,"mustHitSection":true},{"lengthInSteps":16,"typeOfSection":0,"sectionNotes":[[71100,2,0],[71250,0,0],[70800,1,225],[71400,2,225],[71700,1,225]],"altAnim":false,"bpm":200,"changeBPM":false,"mustHitSection":true},{"lengthInSteps":16,"typeOfSection":0,"sectionNotes":[[72000,3,225],[72300,2,0],[72450,0,0],[72600,1,225],[72900,2,0],[73050,0,0]],"altAnim":false,"bpm":200,"changeBPM":false,"mustHitSection":true},{"lengthInSteps":16,"typeOfSection":0,"sectionNotes":[[73200,3,225],[73500,0,225],[73800,2,225],[74100,0,225]],"altAnim":false,"bpm":200,"changeBPM":false,"mustHitSection":true},{"lengthInSteps":16,"typeOfSection":0,"sectionNotes":[[74400,3,225],[74700,0,225],[75000,2,225],[75300,3,225]],"altAnim":false,"bpm":200,"changeBPM":false,"mustHitSection":true},{"lengthInSteps":16,"typeOfSection":0,"sectionNotes":[[76200,1,0],[76350,0,0],[76500,3,225],[75900,2,225],[75600,1,225]],"altAnim":false,"bpm":200,"changeBPM":false,"mustHitSection":true},{"lengthInSteps":16,"typeOfSection":0,"sectionNotes":[[76800,6,225],[76800,1,0],[76950,2,0],[77100,0,0],[77250,2,0],[77400,0,225],[77700,3,225]],"altAnim":false,"bpm":200,"changeBPM":false,"mustHitSection":false},{"lengthInSteps":16,"typeOfSection":0,"sectionNotes":[[78000,2,0],[78150,1,0],[78300,3,0],[78450,1,0],[78600,3,0],[78750,1,0],[78900,2,0],[79050,0,0]],"altAnim":false,"bpm":200,"changeBPM":false,"mustHitSection":false},{"lengthInSteps":16,"typeOfSection":0,"sectionNotes":[[79200,2,0],[79350,0,0],[79500,1,0],[79650,3,0],[79800,2,225],[80100,0,225]],"altAnim":false,"bpm":200,"changeBPM":false,"mustHitSection":false},{"lengthInSteps":16,"typeOfSection":0,"sectionNotes":[[80400,1,225],[80700,2,0],[80850,3,0],[81000,2,225],[81300,3,225]],"altAnim":false,"bpm":200,"changeBPM":false,"mustHitSection":false},{"lengthInSteps":16,"typeOfSection":0,"sectionNotes":[[82200,2,225],[81600,1,225],[81900,1,0],[82050,0,0],[82500,1,225]],"altAnim":false,"bpm":200,"changeBPM":false,"mustHitSection":false},{"lengthInSteps":16,"typeOfSection":0,"sectionNotes":[[82800,0,0],[82950,3,0],[83100,1,0],[83250,2,0],[83400,0,225],[83700,3,225]],"altAnim":false,"bpm":200,"changeBPM":false,"mustHitSection":false},{"lengthInSteps":16,"typeOfSection":0,"sectionNotes":[[84000,0,0],[84150,3,0],[84450,3,0],[84300,1,0],[84600,1,225],[84900,2,225]],"altAnim":false,"bpm":200,"changeBPM":false,"mustHitSection":false},{"lengthInSteps":16,"typeOfSection":0,"sectionNotes":[[85200,0,0],[85350,1,0],[85500,2,0],[85650,0,0],[85800,1,0],[85950,2,0],[86100,0,0],[86250,3,0]],"altAnim":false,"bpm":200,"changeBPM":false,"mustHitSection":false},{"lengthInSteps":16,"typeOfSection":0,"sectionNotes":[[86400,4,225],[86400,2,0],[86550,1,0],[86700,3,0],[86850,1,0],[87000,3,225],[87300,0,225]],"altAnim":false,"bpm":200,"changeBPM":false,"mustHitSection":true},{"lengthInSteps":16,"typeOfSection":0,"sectionNotes":[[87600,1,0],[87750,1,0],[87900,2,0],[88050,0,0],[88200,2,225],[88500,1,225]],"altAnim":false,"bpm":200,"changeBPM":false,"mustHitSection":true},{"lengthInSteps":16,"typeOfSection":0,"sectionNotes":[[88800,1,0],[88950,3,0],[89100,2,0],[89250,0,0],[89400,1,225],[89700,3,225]],"altAnim":false,"bpm":200,"changeBPM":false,"mustHitSection":true},{"lengthInSteps":16,"typeOfSection":0,"sectionNotes":[[90000,1,225],[90300,1,225],[90600,2,0],[90750,0,0],[90900,3,225]],"altAnim":false,"bpm":200,"changeBPM":false,"mustHitSection":true},{"lengthInSteps":16,"typeOfSection":0,"sectionNotes":[[91200,2,225],[91500,2,0],[91650,3,0],[91800,0,375],[92250,2,0]],"altAnim":false,"bpm":200,"changeBPM":false,"mustHitSection":true},{"lengthInSteps":16,"typeOfSection":0,"sectionNotes":[[92400,0,225],[92700,2,225],[93000,1,0],[93150,0,0],[93300,3,225]],"altAnim":false,"bpm":200,"changeBPM":false,"mustHitSection":true},{"lengthInSteps":16,"typeOfSection":0,"sectionNotes":[[93600,2,225],[93900,0,225],[94200,2,0],[94350,1,0],[94500,3,225]],"altAnim":false,"bpm":200,"changeBPM":false,"mustHitSection":true},{"lengthInSteps":16,"typeOfSection":0,"sectionNotes":[[94800,2,0],[94950,1,0],[95100,3,0],[95250,1,0],[95400,2,225],[95700,3,225]],"altAnim":false,"bpm":200,"changeBPM":false,"mustHitSection":true},{"lengthInSteps":16,"typeOfSection":0,"sectionNotes":[[96000,2,525]],"altAnim":false,"bpm":200,"changeBPM":false,"mustHitSection":true},{"lengthInSteps":16,"typeOfSection":0,"sectionNotes":[],"altAnim":false,"bpm":200,"changeBPM":false,"mustHitSection":false},{"lengthInSteps":16,"typeOfSection":0,"sectionNotes":[],"altAnim":false,"bpm":200,"changeBPM":false,"mustHitSection":false},{"lengthInSteps":16,"typeOfSection":0,"sectionNotes":[],"altAnim":false,"bpm":200,"changeBPM":false,"mustHitSection":true},{"lengthInSteps":16,"typeOfSection":0,"sectionNotes":[],"altAnim":false,"bpm":200,"changeBPM":false,"mustHitSection":true},{"lengthInSteps":16,"typeOfSection":0,"sectionNotes":[],"altAnim":false,"bpm":200,"changeBPM":false,"mustHitSection":false},{"lengthInSteps":16,"typeOfSection":0,"sectionNotes":[],"altAnim":false,"bpm":200,"changeBPM":false,"mustHitSection":true},{"lengthInSteps":16,"typeOfSection":0,"sectionNotes":[],"altAnim":false,"bpm":200,"changeBPM":false,"mustHitSection":true},{"sectionNotes":[],"typeOfSection":0,"lengthInSteps":16,"altAnim":false,"mustHitSection":true,"changeBPM":false,"bpm":200},{"sectionNotes":[],"typeOfSection":0,"lengthInSteps":16,"altAnim":false,"mustHitSection":true,"changeBPM":false,"bpm":200},{"sectionNotes":[],"typeOfSection":0,"lengthInSteps":16,"altAnim":false,"mustHitSection":true,"changeBPM":false,"bpm":200},{"sectionNotes":[],"typeOfSection":0,"lengthInSteps":16,"altAnim":false,"mustHitSection":true,"changeBPM":false,"bpm":200},{"sectionNotes":[],"typeOfSection":0,"lengthInSteps":16,"altAnim":false,"mustHitSection":true,"changeBPM":false,"bpm":200},{"sectionNotes":[],"typeOfSection":0,"lengthInSteps":16,"altAnim":false,"mustHitSection":true,"changeBPM":false,"bpm":200},{"sectionNotes":[],"typeOfSection":0,"lengthInSteps":16,"altAnim":false,"mustHitSection":true,"changeBPM":false,"bpm":200},{"sectionNotes":[],"typeOfSection":0,"lengthInSteps":16,"altAnim":false,"mustHitSection":true,"changeBPM":false,"bpm":200},{"sectionNotes":[],"typeOfSection":0,"lengthInSteps":16,"altAnim":false,"mustHitSection":true,"changeBPM":false,"bpm":200},{"sectionNotes":[],"typeOfSection":0,"lengthInSteps":16,"altAnim":false,"mustHitSection":true,"changeBPM":false,"bpm":200},{"sectionNotes":[],"typeOfSection":0,"lengthInSteps":16,"altAnim":false,"mustHitSection":true,"changeBPM":false,"bpm":200},{"sectionNotes":[],"typeOfSection":0,"lengthInSteps":16,"altAnim":false,"mustHitSection":true,"changeBPM":false,"bpm":200},{"sectionNotes":[],"typeOfSection":0,"lengthInSteps":16,"altAnim":false,"mustHitSection":true,"changeBPM":false,"bpm":200},{"lengthInSteps":16,"altAnim":false,"typeOfSection":0,"sectionNotes":[],"bpm":200,"changeBPM":false,"mustHitSection":true}],"player2":"lavtired","song":"tempting old","validScore":true,"sections":0,"needsVoices":true,"bpm":200,"speed":2.8}}